image_converter/__init__.py
image_converter/converter.py
prag_matic_image_converter-0.1.1.dist-info/LICENSE
prag_matic_image_converter-0.1.1.dist-info/METADATA
prag_matic_image_converter-0.1.1.dist-info/WHEEL
prag_matic_image_converter-0.1.1.dist-info/top_level.txt
prag_matic_image_converter-0.1.1.dist-info/RECORD
